{
  "debug_info": {
    "line_score": {
      "line1": 100,
      "line2": 300,
      "line3": 700,
      "line4": 1300,
      "gameover": -500
    },
    "shape_info": {
      "shapeNone": {
        "index": 0,
        "color": "none"
      },
      "shapeI": {
        "index": 1,
        "color": "red"
      },
      "shapeL": {
        "index": 2,
        "color": "green"
      },
      "shapeJ": {
        "index": 3,
        "color": "purple"
      },
      "shapeT": {
        "index": 4,
        "color": "gold"
      },
      "shapeO": {
        "index": 5,
        "color": "pink"
      },
      "shapeS": {
        "index": 6,
        "color": "blue"
      },
      "shapeZ": {
        "index": 7,
        "color": "yellow"
      }
    },
    "line_score_stat": [
      37,
      16,
      1,
      0
    ],
    "shape_info_stat": [
      0,
      30,
      23,
      32,
      27,
      19,
      19,
      31
    ]
  },
  "judge_info": {
    "elapsed_time": 180.506,
    "game_time": 180,
    "gameover_count": 0,
    "score": 11256,
    "line": 72,
    "block_index": 180,
    "block_num_max": -1,
    "mode": "predict"
  }
}
